odoo/addons/email_template_config/README.rst
odoo/addons/email_template_config/__init__.py
odoo/addons/email_template_config/__manifest__.py
odoo/addons/email_template_config/models/__init__.py
odoo/addons/email_template_config/models/mail_template.py
odoo/addons/email_template_config/readme/CONTRIBUTORS.rst
odoo/addons/email_template_config/readme/DESCRIPTION.rst
odoo/addons/email_template_config/static/description/index.html
odoo/addons/email_template_config/views/mail_template_views.xml
odoo12_addon_email_template_config-12.0.1.0.0.99.dev3.dist-info/METADATA
odoo12_addon_email_template_config-12.0.1.0.0.99.dev3.dist-info/WHEEL
odoo12_addon_email_template_config-12.0.1.0.0.99.dev3.dist-info/top_level.txt
odoo12_addon_email_template_config-12.0.1.0.0.99.dev3.dist-info/RECORD
