Metadata-Version: 2.1
Name: odoo12-addon-email-template-config
Version: 12.0.1.0.0.99.dev3
Summary: This module extends the email in order to force some behaviours configured in the mail template(e.g. force send mail or not).
Home-page: https://www.coopiteasy.be
Author: Coop IT Easy SCRLfs
License: AGPL-3
Platform: UNKNOWN
Classifier: Programming Language :: Python
Classifier: Framework :: Odoo
Classifier: License :: OSI Approved :: GNU Affero General Public License v3
Requires-Python: >=3.5
Requires-Dist: odoo (<12.1dev,>=12.0a)
